tinysexpr/__init__.py
tinysexpr-1.4.2.dist-info/WHEEL
tinysexpr-1.4.2.dist-info/METADATA
tinysexpr-1.4.2.dist-info/RECORD
