Metadata-Version: 2.4
Name: tinysexpr
Version: 1.4.2
Summary: A very simple S-expression parser that tries to make as little fuss as possible.
Author: Sebastian Hack
Author-email: Sebastian Hack <contact@s-hack.de>
License-Expression: MIT
Requires-Python: >=3.10
Project-URL: GitHub, https://github.com/shack/tinysexpr
